<openerp>
    <data noupdate="1">
        <record id="cron_sale_order_uuid_generate" model="ir.cron">
            <field name="name">Sale Order Uuid Generate</field>
            <field name="active" eval="False" />
            <field name="user_id" ref="base.user_root" />
            <field name="interval_number">1</field>
            <field name="interval_type">hours</field>
            <field name="numbercall">-1</field>
            <field name="model" eval="'sale.order'" />
            <field name="function" eval="'cron_sale_order_uuid_generate'" />
            <field name="args" eval="" />
        </record>
        <record id="cron_sale_order_upload_to_s3_generate" model="ir.cron">
            <field name="name">Sale Order Upload to S3</field>
            <field name="active" eval="False" />
            <field name="user_id" ref="base.user_root" />
            <field name="interval_number">1</field>
            <field name="interval_type">hours</field>
            <field name="numbercall">-1</field>
            <field name="model" eval="'sale.order'" />
            <field name="function" eval="'cron_sale_order_upload_to_s3_generate'" />
            <field name="args" eval="" />
        </record>                                                        
    </data>
</openerp>